ecmwflibs-0.6.3.dist-info/zip-safe
ecmwflibs-0.6.3.dist-info/RECORD
ecmwflibs-0.6.3.dist-info/LICENSE
ecmwflibs-0.6.3.dist-info/WHEEL
ecmwflibs-0.6.3.dist-info/top_level.txt
ecmwflibs-0.6.3.dist-info/METADATA
ecmwflibs-0.6.3.dist-info/NOTICE.md
ecmwflibs/_ecmwflibs.cpython-310-darwin.so
ecmwflibs/versions.txt
ecmwflibs/__init__.py
ecmwflibs/_ecmwflibs.cc
ecmwflibs/__main__.py
ecmwflibs/etc/README
ecmwflibs/.dylibs/libpango-1.0.0.dylib
ecmwflibs/.dylibs/libpangoft2-1.0.0.dylib
ecmwflibs/.dylibs/libpixman-1.0.42.2.dylib
ecmwflibs/.dylibs/libaec.0.1.2.dylib
ecmwflibs/.dylibs/libgraphite2.3.2.1.dylib
ecmwflibs/.dylibs/libpcre2-8.0.dylib
ecmwflibs/.dylibs/libcairo.2.dylib
ecmwflibs/.dylibs/libglib-2.0.0.dylib
ecmwflibs/.dylibs/libnetcdf.19.dylib
ecmwflibs/.dylibs/libeccodes.dylib
ecmwflibs/.dylibs/libpng16.16.dylib
ecmwflibs/.dylibs/libpangocairo-1.0.0.dylib
ecmwflibs/.dylibs/libgobject-2.0.0.dylib
ecmwflibs/.dylibs/libMagPlus.dylib
ecmwflibs/.dylibs/libfreetype.6.dylib
ecmwflibs/.dylibs/libeccodes_memfs.dylib
ecmwflibs/.dylibs/libharfbuzz.0.dylib
ecmwflibs/.dylibs/libgmodule-2.0.0.dylib
ecmwflibs/.dylibs/libintl.8.dylib
ecmwflibs/.dylibs/libsz.2.0.1.dylib
ecmwflibs/.dylibs/libfribidi.0.dylib
ecmwflibs/.dylibs/libfontconfig.1.dylib
ecmwflibs/.dylibs/libopenjp2.2.5.0.dylib
ecmwflibs/.dylibs/liblzma.5.dylib
ecmwflibs/.dylibs/libjpeg.8.3.2.dylib
ecmwflibs/.dylibs/libproj.25.9.3.1.dylib
ecmwflibs/.dylibs/libhdf5.310.3.0.dylib
ecmwflibs/.dylibs/libzstd.1.5.5.dylib
ecmwflibs/.dylibs/libhdf5_hl.310.0.3.dylib
ecmwflibs/.dylibs/libtiff.6.dylib
ecmwflibs/.dylibs/libgio-2.0.0.dylib
ecmwflibs/copying/libopenjp2.txt
ecmwflibs/copying/libaec.txt
ecmwflibs/copying/libglib.txt
ecmwflibs/copying/libpcre2.txt
ecmwflibs/copying/libfontconfig.txt
ecmwflibs/copying/libintl.txt
ecmwflibs/copying/libproj.txt
ecmwflibs/copying/libfribidi.txt
ecmwflibs/copying/libzstd.txt
ecmwflibs/copying/libtiff.txt
ecmwflibs/copying/libpango.txt
ecmwflibs/copying/libhdf5.txt
ecmwflibs/copying/libpixman.txt
ecmwflibs/copying/.gitignore
ecmwflibs/copying/libszip.txt
ecmwflibs/copying/libpng.txt
ecmwflibs/copying/libfreetype.txt
ecmwflibs/copying/libcairo.txt
ecmwflibs/copying/list.json
