Metadata-Version: 2.1
Name: ecmwflibs
Version: 0.6.3
Summary: Wraps ECMWF tools (experimental)
Home-page: https://github.com/ecmwf/ecmwflibs
Author: ECMWF
Author-email: software.support@ecmwf.int
License: Apache 2.0
Platform: UNKNOWN
Classifier: Development Status :: 3 - Alpha
Classifier: Intended Audience :: Developers
Classifier: Programming Language :: Python
Classifier: Programming Language :: Python :: 3
Classifier: Programming Language :: Python :: 3.6
Classifier: Programming Language :: Python :: 3.7
Classifier: Programming Language :: Python :: 3.8
Classifier: Programming Language :: Python :: Implementation :: CPython
Classifier: Operating System :: OS Independent
License-File: LICENSE
License-File: NOTICE.md
Requires-Dist: findlibs
